permer_py-0.39.0.dist-info/METADATA
permer_py-0.39.0.dist-info/WHEEL
permer_py/__init__.py
permer_py/__init__.pyi
permer_py/py.typed
permer_py/permer_py.cpython-311-aarch64-linux-gnu.so
permer_py-0.39.0.dist-info/RECORD
